README.md
setup.py
grpc_micorservice_discover.egg-info/PKG-INFO
grpc_micorservice_discover.egg-info/SOURCES.txt
grpc_micorservice_discover.egg-info/dependency_links.txt
grpc_micorservice_discover.egg-info/requires.txt
grpc_micorservice_discover.egg-info/top_level.txt
grpc_microservice/__init__.py
grpc_microservice/common/__init__.py
grpc_microservice/common/exceptions.py
grpc_microservice/common/meta_cls.py
grpc_microservice/common/pbjson.py
grpc_microservice/common/client/__init__.py
grpc_microservice/common/client/generic_client_interceptor.py
grpc_microservice/common/client/header_manipulator_client_interceptor.py
grpc_microservice/common/server/__init__.py
grpc_microservice/common/server/key_pool.py
grpc_microservice/common/server/request_header_validator_interceptor.py
grpc_microservice/etcd_minoter/__init__.py
grpc_microservice/etcd_minoter/etcd_manager.py
grpc_microservice/etcd_minoter/client/__init__.py
grpc_microservice/etcd_minoter/client/client_discovery.py
grpc_microservice/etcd_minoter/client/load_balance.py
grpc_microservice/etcd_minoter/server/__init__.py
grpc_microservice/etcd_minoter/server/server_register.py
grpc_microservice/etcd_minoter/server/sys_util.py
grpc_microservice/etcd_minoter/test/__init__.py
grpc_microservice/etcd_minoter/test/kazoo_create_node_test.py
grpc_microservice/etcd_minoter/test/kazoo_more_room_test.py
grpc_microservice/etcd_minoter/test/kazoo_sgin_room_gevent_test.py
grpc_microservice/example/__init__.py
grpc_microservice/example/reg_etcdv3/__init__.py
grpc_microservice/example/reg_etcdv3/server_start.py
grpc_microservice/example/reg_etcdv3/smart_client.py
grpc_microservice/example/reg_etcdv3/room_proto/__init__.py
grpc_microservice/example/reg_etcdv3/room_proto/room_server_pb2.py
grpc_microservice/example/reg_etcdv3/room_proto/room_server_pb2_grpc.py
grpc_microservice/example/reg_zk/__init__.py
grpc_microservice/example/reg_zk/server_start.py
grpc_microservice/example/reg_zk/smart_client.py
grpc_microservice/example/reg_zk/room_proto/__init__.py
grpc_microservice/example/reg_zk/room_proto/room_server_pb2.py
grpc_microservice/example/reg_zk/room_proto/room_server_pb2_grpc.py
grpc_microservice/zk_minoter/__init__.py
grpc_microservice/zk_minoter/grpc_decorate.py
